adpix/__init__.py
adpix/rest/__init__.py
adpix/rest/client.py
adpix-1.5.2.dist-info/DESCRIPTION.rst
adpix-1.5.2.dist-info/METADATA
adpix-1.5.2.dist-info/RECORD
adpix-1.5.2.dist-info/WHEEL
adpix-1.5.2.dist-info/metadata.json
adpix-1.5.2.dist-info/top_level.txt
