Metadata-Version: 2.0
Name: adpix
Version: 1.5.2
Summary: Python client for adPix API services.
Home-page: http://adpix.snshine.in/
Author: Surya Teja Cheedella
Author-email: surya@snshine.in
License: Apache 2.0
Platform: UNKNOWN
Requires-Dist: python-magic (>0.4.12)
Requires-Dist: requests (>2.13.0)
